ecs_composex_mongodb_iam_user/__init__.py
ecs_composex_mongodb_iam_user/mongodb_atlas_awsiamdatabaseuser.py
ecs_composex_mongodb_iam_user/mongodb_iam_user.py
ecs_composex_mongodb_iam_user/mongodb_iam_user_params.py
ecs_composex_mongodb_iam_user/mongodb_iam_user_stack.py
ecs_composex_mongodb_iam_user/mongodb_iam_user_template.py
ecs_composex_mongodb_iam_user/x-mongodb_iam_user.spec.json
ecs_composex_mongodb_iam_user-0.1.0.dist-info/LICENSE
ecs_composex_mongodb_iam_user-0.1.0.dist-info/WHEEL
ecs_composex_mongodb_iam_user-0.1.0.dist-info/METADATA
ecs_composex_mongodb_iam_user-0.1.0.dist-info/RECORD
